pylibrus/__init__.py
pylibrus/api.py
pylibrus/auth.py
pylibrus/exceptions.py
pylibrus/resources.py
pylibrus-0.0.1.dist-info/LICENSE
pylibrus-0.0.1.dist-info/METADATA
pylibrus-0.0.1.dist-info/WHEEL
pylibrus-0.0.1.dist-info/top_level.txt
pylibrus-0.0.1.dist-info/RECORD
