Metadata-Version: 2.1
Name: pylibrus
Version: 0.0.1
Summary: Librus (polish school e-register) unofficial API client written in Python.
Home-page: https://github.com/ChimekKoo/pylibrus
Author: Joachim Kołodziejski
Author-email: kolodziejski.joachim@gmail.com
Project-URL: Source, https://github.com/ChimekKoo/pylibrus
Project-URL: Bug Tracker, https://github.com/ChimekKoo/pylibrus/issues
Classifier: Programming Language :: Python :: 3
Classifier: License :: OSI Approved :: MIT License
Classifier: Operating System :: OS Independent
License-File: LICENSE
Requires-Dist: requests (>=2.0.0)
